{
	"type":"minecraft:crafting_shapeless",
	"ingredients": [
		{"item":"denominatingcurrency:penny_cent"},
		{"item":"denominatingcurrency:penny_cent"},
		{"item":"denominatingcurrency:penny_cent"},
		{"item":"denominatingcurrency:penny_cent"},
		{"item":"denominatingcurrency:penny_cent"},
		{"item":"denominatingcurrency:nickel_cent"},
		{"item":"denominatingcurrency:nickel_cent"},
		{"item":"denominatingcurrency:dime_cent"},
		{"item":"denominatingcurrency:quarter_cent"}
	],
	"result": {
		"item":"denominatingcurrency:half_cent"
	}
}